ip_geo_locator/_init_.py
ip_geo_locator/ip_api.py
ip_geo_locator-0.1.3.dist-info/METADATA
ip_geo_locator-0.1.3.dist-info/WHEEL
ip_geo_locator-0.1.3.dist-info/top_level.txt
ip_geo_locator-0.1.3.dist-info/RECORD
